{"url": "https://navbharattimes.indiatimes.com/movie-masti/news-from-bollywood/kartik-aaryan-apologised-pankaj-tripathi-for-slapping-him-during-shooting-of-luka-chuppi/articleshow/68206498.cms\n", "description": "Bollywood News: \u0915\u093e\u0930\u094d\u0924\u093f\u0915 \u0906\u0930\u094d\u092f\u0928 \u0914\u0930 \u0915\u0943\u0924\u093f \u0938\u0947\u0928\u0928 \u0915\u0940 \u092b\u093f\u0932\u094d\u092e \u0932\u0941\u0915\u093e-\u091b\u0941\u092a\u0940 \u0938\u0947 \u091c\u0941\u0921\u093c\u093e \u090f\u0915 \u092e\u091c\u0947\u0926\u093e\u0930 \u0915\u093f\u0938\u094d\u0938\u093e \u0938\u093e\u092e\u0928\u0947 \u0906\u092f\u093e \u0939\u0948\u0964 \u0907\u0938 \u0915\u093f\u0938\u094d\u0938\u0947 \u0915\u094b \u091c\u093e\u0928\u0915\u0930 \u0906\u092a\u0915\u094b \u0915\u093e\u0930\u094d\u0924\u093f\u0915 \u0906\u0930\u094d\u092f\u0928 \u092a\u0930 \u092a\u094d\u092f\u093e\u0930 \u0906 \u091c\u093e\u090f\u0917\u093e\u0964", "date_publish": "28/02/2019, 21:07:50", "authors": [], "title": "\u091c\u092c \u0915\u093e\u0930\u094d\u0924\u093f\u0915 \u0906\u0930\u094d\u092f\u0928 \u0928\u0947 \u092e\u093e\u0930\u093e \u092a\u0902\u0915\u091c \u0924\u094d\u0930\u093f\u092a\u093e\u0920\u0940 \u0915\u094b \u0925\u092a\u094d\u092a\u0921\u093c", "image_url": "https://navbharattimes.indiatimes.com/thumb/msid-68206498,width-650,resizemode-4/weather.jpg", "text": "Navbharat Times has updated its Privacy and Cookie policy. We use cookies to ensure that we give you the better experience on our website. If you continue without changing your settings, we'll assume that you are happy to receive all cookies on the Navbharat Times website. However, you can change your cookie setting at any time by clicking on our Cookie Policy link at any time. You can also see our Privacy Policy"}